{
  "experiment_type": "external_kaggle_uci",
  "model": "rf",
  "variant": "intercept_only",
  "split_mode": "holdout",
  "n_calibration": 34363,
  "n_evaluation": 34363,
  "metrics_before": {
    "brier_score": 0.23230335853482148,
    "ece": 0.06533362226536771,
    "mce": 0.24154312221029572,
    "bin_details": [
      {
        "lo": 0.30000000000000004,
        "hi": 0.4,
        "acc": 0.20781312927909787,
        "conf": 0.3924820908657308,
        "n": 4966
      },
      {
        "lo": 0.4,
        "hi": 0.5,
        "acc": 0.45749768039397615,
        "conf": 0.46348316287560815,
        "n": 14011
      },
      {
        "lo": 0.5,
        "hi": 0.6000000000000001,
        "acc": 0.588040356432727,
        "conf": 0.5285615890874541,
        "n": 13579
      },
      {
        "lo": 0.6000000000000001,
        "hi": 0.7000000000000001,
        "acc": 0.8588821250691754,
        "conf": 0.6173390028588797,
        "n": 1807
      }
    ],
    "calibration_curve": {
      "fraction_pos": [
        0.20781312927909787,
        0.45749768039397615,
        0.588040356432727,
        0.8588821250691754
      ],
      "mean_predicted": [
        0.392482090865729,
        0.4634831628756043,
        0.5285615890874771,
        0.617339002858875
      ]
    }
  },
  "metrics_after": {
    "brier_score": 0.2323432643058989,
    "ece": 0.06503493939163604,
    "mce": 0.23817486495594908,
    "bin_details": [
      {
        "lo": 0.30000000000000004,
        "hi": 0.4,
        "acc": 0.20781312927909787,
        "conf": 0.3902156330702915,
        "n": 4966
      },
      {
        "lo": 0.4,
        "hi": 0.5,
        "acc": 0.4577619893428064,
        "conf": 0.4612978238962284,
        "n": 14075
      },
      {
        "lo": 0.5,
        "hi": 0.6000000000000001,
        "acc": 0.5929622614017194,
        "conf": 0.5274595051232251,
        "n": 13726
      },
      {
        "lo": 0.6000000000000001,
        "hi": 0.7000000000000001,
        "acc": 0.8552631578947368,
        "conf": 0.6170882929387878,
        "n": 1596
      }
    ],
    "calibration_curve": {
      "fraction_pos": [
        0.20781312927909787,
        0.4577619893428064,
        0.5929622614017194,
        0.8552631578947368
      ],
      "mean_predicted": [
        0.3902156330702756,
        0.4612978238962111,
        0.5274595051232143,
        0.6170882929387876
      ]
    }
  },
  "improvement": {
    "brier_delta": -3.9905771077430874e-05,
    "ece_delta": 0.0002986828737316649,
    "mce_delta": 0.0033682572543466405
  },
  "per_fold_params": [
    {
      "intercept": -0.009516307609346384,
      "slope": 1.0
    }
  ],
  "mean_params": {
    "intercept": -0.009516307609346384,
    "slope": 1.0
  },
  "train_site": "va",
  "test_site": "kaggle",
  "experiment_variant": "cfs"
}