{
  "experiment_type": "external_kaggle_uci",
  "model": "lr",
  "variant": "intercept_slope",
  "split_mode": "holdout",
  "n_calibration": 34363,
  "n_evaluation": 34363,
  "metrics_before": {
    "brier_score": 0.26659540184624914,
    "ece": 0.13853946098860898,
    "mce": 0.13853946098860898,
    "bin_details": [
      {
        "lo": 0.30000000000000004,
        "hi": 0.4,
        "acc": 0.4941070337281378,
        "conf": 0.3555675727395288,
        "n": 34363
      }
    ],
    "calibration_curve": {
      "fraction_pos": [
        0.4941070337281378
      ],
      "mean_predicted": [
        0.35556757273952116
      ]
    }
  },
  "metrics_after": {
    "brier_score": 0.23506567747683596,
    "ece": 0.08723658313397709,
    "mce": 0.8226083663774351,
    "bin_details": [
      {
        "lo": 0.1,
        "hi": 0.2,
        "acc": 1.0,
        "conf": 0.17739163362256496,
        "n": 1
      },
      {
        "lo": 0.2,
        "hi": 0.30000000000000004,
        "acc": 0.08378378378378379,
        "conf": 0.2848757424665287,
        "n": 740
      },
      {
        "lo": 0.30000000000000004,
        "hi": 0.4,
        "acc": 0.27815765707650625,
        "conf": 0.36119802821612107,
        "n": 7751
      },
      {
        "lo": 0.4,
        "hi": 0.5,
        "acc": 0.563502071698793,
        "conf": 0.4455360179447636,
        "n": 11102
      },
      {
        "lo": 0.5,
        "hi": 0.6000000000000001,
        "acc": 0.5335285956528442,
        "conf": 0.5465502802192722,
        "n": 6487
      },
      {
        "lo": 0.6000000000000001,
        "hi": 0.7000000000000001,
        "acc": 0.5503111246016087,
        "conf": 0.6457670659712513,
        "n": 6589
      },
      {
        "lo": 0.7000000000000001,
        "hi": 0.8,
        "acc": 0.8369696969696969,
        "conf": 0.7275710436331702,
        "n": 1650
      },
      {
        "lo": 0.8,
        "hi": 0.9,
        "acc": 0.8372093023255814,
        "conf": 0.8177590816606018,
        "n": 43
      }
    ],
    "calibration_curve": {
      "fraction_pos": [
        1.0,
        0.08378378378378379,
        0.27815765707650625,
        0.563502071698793,
        0.5335285956528442,
        0.5503111246016087,
        0.8369696969696969,
        0.8372093023255814
      ],
      "mean_predicted": [
        0.17739163362256496,
        0.284875742466529,
        0.3611980282161178,
        0.4455360179447686,
        0.5465502802192671,
        0.6457670659712487,
        0.7275710436331697,
        0.8177590816606018
      ]
    }
  },
  "improvement": {
    "brier_delta": 0.031529724369413176,
    "ece_delta": 0.05130287785463189,
    "mce_delta": -0.684068905388826
  },
  "per_fold_params": [
    {
      "intercept": 6.21279056348602,
      "slope": 10.475169366373407
    }
  ],
  "mean_params": {
    "intercept": 6.21279056348602,
    "slope": 10.475169366373407
  },
  "train_site": "hungary",
  "test_site": "kaggle",
  "experiment_variant": "cfs"
}