{
  "experiment_type": "external_uci",
  "model": "xgb",
  "variant": "intercept_only",
  "split_mode": "holdout",
  "n_calibration": 61,
  "n_evaluation": 62,
  "metrics_before": {
    "brier_score": 0.246904247413671,
    "ece": 0.39168146601127035,
    "mce": 0.7541489526629448,
    "bin_details": [
      {
        "lo": 0.0,
        "hi": 0.1,
        "acc": 0.0,
        "conf": 0.04954533651471138,
        "n": 2
      },
      {
        "lo": 0.1,
        "hi": 0.2,
        "acc": 0.75,
        "conf": 0.18763884902000427,
        "n": 4
      },
      {
        "lo": 0.2,
        "hi": 0.30000000000000004,
        "acc": 1.0,
        "conf": 0.2458510473370552,
        "n": 4
      },
      {
        "lo": 0.30000000000000004,
        "hi": 0.4,
        "acc": 1.0,
        "conf": 0.36714397536383736,
        "n": 9
      },
      {
        "lo": 0.4,
        "hi": 0.5,
        "acc": 1.0,
        "conf": 0.42399762570858,
        "n": 6
      },
      {
        "lo": 0.5,
        "hi": 0.6000000000000001,
        "acc": 1.0,
        "conf": 0.5490996638933817,
        "n": 15
      },
      {
        "lo": 0.6000000000000001,
        "hi": 0.7000000000000001,
        "acc": 0.875,
        "conf": 0.6540149971842766,
        "n": 8
      },
      {
        "lo": 0.7000000000000001,
        "hi": 0.8,
        "acc": 1.0,
        "conf": 0.7589577039082845,
        "n": 3
      },
      {
        "lo": 0.8,
        "hi": 0.9,
        "acc": 0.875,
        "conf": 0.8392333462834358,
        "n": 8
      },
      {
        "lo": 0.9,
        "hi": 1.0,
        "acc": 1.0,
        "conf": 0.9244146148363749,
        "n": 3
      }
    ],
    "calibration_curve": {
      "fraction_pos": [
        0.0,
        0.75,
        1.0,
        1.0,
        1.0,
        1.0,
        0.875,
        1.0,
        0.875,
        1.0
      ],
      "mean_predicted": [
        0.04954533651471138,
        0.18763884902000427,
        0.2458510473370552,
        0.36714397536383736,
        0.42399762570858,
        0.5490996638933817,
        0.6540149971842766,
        0.7589577039082845,
        0.8392333462834358,
        0.9244146148363749
      ]
    }
  },
  "metrics_after": {
    "brier_score": 0.05483670211082195,
    "ece": 0.022330595403298587,
    "mce": 0.5030662206312775,
    "bin_details": [
      {
        "lo": 0.5,
        "hi": 0.6000000000000001,
        "acc": 0.0,
        "conf": 0.5030662206312775,
        "n": 2
      },
      {
        "lo": 0.7000000000000001,
        "hi": 0.8,
        "acc": 1.0,
        "conf": 0.7979119579579355,
        "n": 1
      },
      {
        "lo": 0.8,
        "hi": 0.9,
        "acc": 0.8571428571428571,
        "conf": 0.8456748102911092,
        "n": 7
      },
      {
        "lo": 0.9,
        "hi": 1.0,
        "acc": 0.9615384615384616,
        "conf": 0.9596923056973528,
        "n": 52
      }
    ],
    "calibration_curve": {
      "fraction_pos": [
        0.0,
        1.0,
        0.8571428571428571,
        0.9615384615384616
      ],
      "mean_predicted": [
        0.5030662206312775,
        0.7979119579579355,
        0.8456748102911092,
        0.9596923056973529
      ]
    }
  },
  "improvement": {
    "brier_delta": 0.19206754530284906,
    "ece_delta": 0.3693508706079718,
    "mce_delta": 0.2510827320316673
  },
  "per_fold_params": [
    {
      "intercept": 2.9663842467127246,
      "slope": 1.0
    }
  ],
  "mean_params": {
    "intercept": 2.9663842467127246,
    "slope": 1.0
  },
  "train_sites": [
    "hungary"
  ],
  "test_site": "switzerland"
}