{
  "experiment_type": "external_uci",
  "model": "xgb",
  "method": "isotonic",
  "split_mode": "holdout",
  "n_calibration": 151,
  "n_evaluation": 152,
  "metrics_before": {
    "brier_score": 0.23957579205707616,
    "ece": 0.22074909076878899,
    "mce": 0.3852202500167646,
    "bin_details": [
      {
        "lo": 0.2,
        "hi": 0.30000000000000004,
        "acc": 0.0,
        "conf": 0.27036712467670443,
        "n": 10
      },
      {
        "lo": 0.30000000000000004,
        "hi": 0.4,
        "acc": 0.2,
        "conf": 0.35644773542881014,
        "n": 10
      },
      {
        "lo": 0.4,
        "hi": 0.5,
        "acc": 0.23076923076923078,
        "conf": 0.4531782269477844,
        "n": 13
      },
      {
        "lo": 0.5,
        "hi": 0.6000000000000001,
        "acc": 0.21052631578947367,
        "conf": 0.5578702468621103,
        "n": 19
      },
      {
        "lo": 0.6000000000000001,
        "hi": 0.7000000000000001,
        "acc": 0.5,
        "conf": 0.6604513168334961,
        "n": 20
      },
      {
        "lo": 0.7000000000000001,
        "hi": 0.8,
        "acc": 0.3684210526315789,
        "conf": 0.7536413026483435,
        "n": 38
      },
      {
        "lo": 0.8,
        "hi": 0.9,
        "acc": 0.8108108108108109,
        "conf": 0.8515294258658951,
        "n": 37
      },
      {
        "lo": 0.9,
        "hi": 1.0,
        "acc": 1.0,
        "conf": 0.9118246078491211,
        "n": 5
      }
    ],
    "calibration_curve": {
      "fraction_pos": [
        0.0,
        0.2,
        0.23076923076923078,
        0.21052631578947367,
        0.5,
        0.3684210526315789,
        0.8108108108108109,
        1.0
      ],
      "mean_predicted": [
        0.27036712467670443,
        0.35644773542881014,
        0.4531782269477844,
        0.5578702468621103,
        0.6604513168334961,
        0.7536413026483435,
        0.8515294258658951,
        0.9118246078491211
      ]
    }
  },
  "metrics_after": {
    "brier_score": 0.19097736012648303,
    "ece": 0.07997432135754537,
    "mce": 0.26577122491870886,
    "bin_details": [
      {
        "lo": 0.0,
        "hi": 0.1,
        "acc": 0.05263157894736842,
        "conf": 0.004398716586742593,
        "n": 19
      },
      {
        "lo": 0.1,
        "hi": 0.2,
        "acc": 0.28,
        "conf": 0.17946655696712244,
        "n": 25
      },
      {
        "lo": 0.2,
        "hi": 0.30000000000000004,
        "acc": 0.0,
        "conf": 0.26577122491870886,
        "n": 2
      },
      {
        "lo": 0.30000000000000004,
        "hi": 0.4,
        "acc": 0.3548387096774194,
        "conf": 0.31242936592909826,
        "n": 31
      },
      {
        "lo": 0.4,
        "hi": 0.5,
        "acc": 0.3333333333333333,
        "conf": 0.42857142857142855,
        "n": 6
      },
      {
        "lo": 0.6000000000000001,
        "hi": 0.7000000000000001,
        "acc": 0.45454545454545453,
        "conf": 0.6278278643735329,
        "n": 22
      },
      {
        "lo": 0.7000000000000001,
        "hi": 0.8,
        "acc": 0.7391304347826086,
        "conf": 0.7600943435937435,
        "n": 23
      },
      {
        "lo": 0.8,
        "hi": 0.9,
        "acc": 0.6666666666666666,
        "conf": 0.886534988409343,
        "n": 6
      },
      {
        "lo": 0.9,
        "hi": 1.0,
        "acc": 0.8,
        "conf": 0.9390165717758474,
        "n": 5
      }
    ],
    "calibration_curve": {
      "fraction_pos": [
        0.05263157894736842,
        0.28,
        0.0,
        0.3548387096774194,
        0.3333333333333333,
        0.45454545454545453,
        0.7391304347826086,
        0.6666666666666666,
        0.8888888888888888
      ],
      "mean_predicted": [
        0.004398716586742593,
        0.1794665569671224,
        0.26577122491870886,
        0.31242936592909826,
        0.42857142857142855,
        0.6278278643735329,
        0.7600943435937436,
        0.886534988409343,
        0.9830601588266243
      ]
    }
  },
  "improvement": {
    "brier_delta": 0.04859843193059313,
    "ece_delta": 0.14077476941124362,
    "mce_delta": 0.11944902509805572
  },
  "train_sites": [
    "va"
  ],
  "test_site": "cleveland"
}