{
  "experiment_type": "external_uci",
  "model": "xgb",
  "calibration_metrics": {
    "brier_score": 0.1965021857358167,
    "ece": 0.1503050182759762,
    "mce": 0.34260496248801553,
    "bin_details": [
      {
        "lo": 0.0,
        "hi": 0.1,
        "acc": 0.0,
        "conf": 0.06555052101612091,
        "n": 1
      },
      {
        "lo": 0.1,
        "hi": 0.2,
        "acc": 0.5,
        "conf": 0.1573950375119845,
        "n": 6
      },
      {
        "lo": 0.2,
        "hi": 0.30000000000000004,
        "acc": 0.45454545454545453,
        "conf": 0.2334142110564492,
        "n": 11
      },
      {
        "lo": 0.30000000000000004,
        "hi": 0.4,
        "acc": 0.6,
        "conf": 0.34355700373649595,
        "n": 25
      },
      {
        "lo": 0.4,
        "hi": 0.5,
        "acc": 0.6551724137931034,
        "conf": 0.45111810749974746,
        "n": 29
      },
      {
        "lo": 0.5,
        "hi": 0.6000000000000001,
        "acc": 0.7272727272727273,
        "conf": 0.5405844937671315,
        "n": 22
      },
      {
        "lo": 0.6000000000000001,
        "hi": 0.7000000000000001,
        "acc": 0.7272727272727273,
        "conf": 0.6392316926609386,
        "n": 11
      },
      {
        "lo": 0.7000000000000001,
        "hi": 0.8,
        "acc": 0.8064516129032258,
        "conf": 0.7671035451273764,
        "n": 31
      },
      {
        "lo": 0.8,
        "hi": 0.9,
        "acc": 0.9545454545454546,
        "conf": 0.8498271283778277,
        "n": 44
      },
      {
        "lo": 0.9,
        "hi": 1.0,
        "acc": 0.8,
        "conf": 0.9137870460748673,
        "n": 20
      }
    ],
    "calibration_curve": {
      "fraction_pos": [
        0.0,
        0.5,
        0.45454545454545453,
        0.6,
        0.6551724137931034,
        0.7272727272727273,
        0.7272727272727273,
        0.8064516129032258,
        0.9545454545454546,
        0.8
      ],
      "mean_predicted": [
        0.06555052101612091,
        0.1573950375119845,
        0.2334142110564492,
        0.34355700373649595,
        0.45111810749974746,
        0.5405844937671315,
        0.6392316926609386,
        0.7671035451273764,
        0.8498271283778277,
        0.9137870460748673
      ]
    }
  },
  "n": 200,
  "train_sites": [
    "hungary"
  ],
  "test_site": "va",
  "flags": {
    "ece_moderate": true,
    "ece_severe": true,
    "mce_large": true
  }
}